er_evaluation/__init__.py
er_evaluation/data_structures/__init__.py
er_evaluation/data_structures/_data_structures.py
er_evaluation/datasets/__init__.py
er_evaluation/datasets/patentsview.py
er_evaluation/datasets/rldata.py
er_evaluation/datasets/raw_data/__init__.py
er_evaluation/datasets/raw_data/patentsview/__init__.py
er_evaluation/datasets/raw_data/patentsview/pv-data.parquet
er_evaluation/datasets/raw_data/patentsview/pv-predictions.parquet
er_evaluation/datasets/raw_data/patentsview/pv-reference.parquet
er_evaluation/datasets/raw_data/patentsview/reproduce.ipynb
er_evaluation/datasets/raw_data/rldata/RLdata10000.tsv
er_evaluation/datasets/raw_data/rldata/RLdata500.tsv
er_evaluation/datasets/raw_data/rldata/__init__.py
er_evaluation/datasets/raw_data/rldata/identity.RLdata10000.tsv
er_evaluation/datasets/raw_data/rldata/identity.RLdata500.tsv
er_evaluation/error_analysis/__init__.py
er_evaluation/error_analysis/_cluster_error.py
er_evaluation/error_analysis/_record_error.py
er_evaluation/error_analysis/_subgroup_discovery.py
er_evaluation/estimators/__init__.py
er_evaluation/estimators/_estimators.py
er_evaluation/estimators/_summary_estimators.py
er_evaluation/estimators/_utils.py
er_evaluation/estimators/from_table.py
er_evaluation/metrics/__init__.py
er_evaluation/metrics/_metrics.py
er_evaluation/plots/__init__.py
er_evaluation/plots/_dtree_data.py
er_evaluation/plots/_dtree_plots.py
er_evaluation/plots/_fairness.py
er_evaluation/plots/_plots.py
er_evaluation/search/__init__.py
er_evaluation/search/elasticsearch.py
er_evaluation/search/http_requests.py
er_evaluation/summary/__init__.py
er_evaluation/summary/_summary.py
er_evaluation/utils/__init__.py
er_evaluation/utils/_utils.py
tests/__init__.py
tests/test_notebooks.py
tests/notebooks/__init__.py
tests/notebooks/test_internal_consistency.ipynb
tests/test_data_structures/__init__.py
tests/test_data_structures/test_membership.py
tests/test_datasets/__init__.py
tests/test_datasets/test_datasets.py
ER_Evaluation-2.3.0.dist-info/AUTHORS.rst
ER_Evaluation-2.3.0.dist-info/LICENSE
ER_Evaluation-2.3.0.dist-info/METADATA
ER_Evaluation-2.3.0.dist-info/WHEEL
ER_Evaluation-2.3.0.dist-info/top_level.txt
ER_Evaluation-2.3.0.dist-info/RECORD
