Metadata-Version: 2.1
Name: ER-Evaluation
Version: 2.3.0
Summary: An End-to-End Evaluation Framework for Entity Resolution Systems.
Home-page: https://github.com/OlivierBinette/er_evaluation
Author: Olivier Binette
Author-email: olivier.binette@gmail.com
License: GNU Affero General Public License v3
Keywords: er_evaluation
Classifier: Development Status :: 2 - Pre-Alpha
Classifier: Intended Audience :: Developers
Classifier: Natural Language :: English
Classifier: Programming Language :: Python :: 3
Classifier: Programming Language :: Python :: 3.7
Classifier: Programming Language :: Python :: 3.8
Classifier: Programming Language :: Python :: 3.9
Classifier: Programming Language :: Python :: 3.10
Classifier: Programming Language :: Python :: 3.11
Requires-Python: >=3.6
License-File: LICENSE
License-File: AUTHORS.rst
Requires-Dist: pandas
Requires-Dist: numpy
Requires-Dist: scipy
Requires-Dist: plotly
Requires-Dist: igraph
Requires-Dist: scikit-learn
Requires-Dist: pyarrow
Requires-Dist: urllib3
Requires-Dist: requests
Provides-Extra: test
Requires-Dist: pandas ; extra == 'test'
Requires-Dist: numpy ; extra == 'test'
Requires-Dist: scipy ; extra == 'test'
Requires-Dist: plotly ; extra == 'test'
Requires-Dist: igraph ; extra == 'test'
Requires-Dist: scikit-learn ; extra == 'test'
Requires-Dist: pyarrow ; extra == 'test'
Requires-Dist: urllib3 ; extra == 'test'
Requires-Dist: requests ; extra == 'test'
Requires-Dist: pytest >=3 ; extra == 'test'
Requires-Dist: testbook ; extra == 'test'
Requires-Dist: jupyter ; extra == 'test'
Requires-Dist: pyhamcrest ; extra == 'test'
Requires-Dist: wheel ; extra == 'test'
